Metadata-Version: 2.1
Name: open-image-cli
Version: 0.5.1
Summary: UNKNOWN
Home-page: https://github.com/youngfreeFJS/imagecli
Author: youngfreefjs
License: UNKNOWN
Platform: UNKNOWN
License-File: LICENSE
